{
  "arbalest_loaded": {
    "sounds": [
      "artifex:arbalest_loaded"
    ],
    "subtitle": "artifex.subtitle.arbalest_loaded"
  },
  "arbalest_shoot": {
    "sounds": [
      "artifex:arbalest_shoot"
    ],
    "subtitle": "artifex.subtitle.arbalest_shoot"
  },
  "arbalest_start": {
    "sounds": [
      "artifex:arbalest_start"
    ],
    "subtitle": "artifex.subtitle.arbalest_start"
  },
  "execute": {
    "sounds": [
      "artifex:execute"
    ],
    "subtitle": "artifex.subtitle.execute"
  },
  "iaijutsu": {
    "sounds": [
      "artifex:iaijutsu"
    ],
    "subtitle": "artifex.subtitle.iaijutsu"
  },
  "longbow_shoot": {
    "sounds": [
      "artifex:longbow_shoot"
    ],
    "subtitle": "artifex.subtitle.longbow_shoot"
  },
  "shockwave": {
    "sounds": [
      "artifex:shockwave"
    ],
    "subtitle": "artifex.subtitle.shockwave"
  },
  "throwable_impact": {
    "sounds": [
      "artifex:throwable_impact"
    ],
    "subtitle": "artifex.subtitle.throwable_impact"
  },
  "throwable_thrown": {
    "sounds": [
      "artifex:throwable_thrown"
    ],
    "subtitle": "artifex.subtitle.throwable_thrown"
  }
}